{"status":"OK","list":[{"uuid":"452e231d-ecf5-3d30-b441-94455624a1e5","title":"2014数学","activityid":"671401","qrcode":"","cover":"http://ts3.tvm.cn/ky5d4g/3d/1c/3d1c3e7e-5957-35a5-c3ce-16520e24531b/userimg.jpg","mpuser":"blade.big@gmail.com","addtime":"2016-04-26 12:12:51","startTime":"2016-04-26 12:12:51","startTimeStamp":"1461643971000","endTime":"2016-04-26 13:42:51","coursestatus":"2","boxalias":"BC-EE-7B-89-BD-BB","boxid":"BC-EE-7B-89-BD-BB","desc":"","type":"0","videoUrl":"","download":"1","courseDuration":"5400000"},{"uuid":"5a5818b9-ab72-3b1b-8fe8-bc887d9de971","title":"eQPPT0719（少年）","activityid":"476614","qrcode":"","cover":"http://ts3.tvm.cn/ky5d4g/11/93/119308ff-3704-9739-60a0-325bc119966d/userimg.jpg","mpuser":"blade.big@gmail.com","addtime":"2016-03-16 21:22:10","startTime":"2016-03-16 21:22:10","startTimeStamp":"1458134530000","endTime":"2016-03-16 22:52:10","coursestatus":"2","boxalias":"38-2C-4A-B6-38-2F","boxid":"38-2C-4A-B6-38-2F","desc":"","type":"2","videoUrl":"","download":"0","courseDuration":"5400000"},{"uuid":"248ef3d8-2914-37bb-8aa6-4f28d27207e7","title":"eQPPT0719（少年）","activityid":"255806","qrcode":"","cover":"http://ts3.tvm.cn/ky5d4g/9c/a1/9ca125ef-49ae-c179-1c53-b501f0c5abba/userimg.jpg","mpuser":"blade.big@gmail.com","addtime":"2016-03-16 20:43:00","startTime":"2016-03-16 20:43:00","startTimeStamp":"1458132180000","endTime":"2016-03-16 21:21:55","coursestatus":"2","boxalias":"38-2C-4A-B6-38-2F","boxid":"38-2C-4A-B6-38-2F","desc":"","type":"2","videoUrl":"","download":"0","courseDuration":"2335000"},{"uuid":"cbf5fb74-0c4d-389c-904b-6631c45f4243","title":"PPT探究铁及其化合物（1）","activityid":"763627","qrcode":"","cover":"http://ts3.tvm.cn/ky5d4g/18/4b/184bfd28-b84c-1268-97d1-e72bc4e4af06/userimg.jpg","mpuser":"blade.big@gmail.com","addtime":"2016-03-14 14:58:51","startTime":"2016-03-14 14:58:51","startTimeStamp":"1457938731000","endTime":"2016-03-14 16:28:51","coursestatus":"2","boxalias":"38-2C-4A-B6-38-2F","boxid":"38-2C-4A-B6-38-2F","desc":"","type":"2","videoUrl":"","download":"0","courseDuration":"5400000"},{"uuid":"74c8ab73-e962-3fc7-9933-2a583e7b9308","title":"45-企业文化浅探","activityid":"736786","qrcode":"","cover":"http://ts3.tvm.cn/ky5d4g/3e/71/3e71e008-2eb9-8aa5-0d51-18a4a5e8d2be/userimg.jpg","mpuser":"blade.big@gmail.com","addtime":"2016-03-10 15:56:32","startTime":"2016-03-10 15:56:32","startTimeStamp":"1457596592000","endTime":"2016-03-10 17:26:32","coursestatus":"2","boxalias":"20-18-0E-02-F4-32","boxid":"20-18-0E-02-F4-32","desc":"","type":"2","videoUrl":"http://ts3.tvm.cn/ky5d4g/6b/7b/6b7b3196-ae6e-d6d2-5074-e95eb3df207e/mp4h.mp4","download":"1","courseDuration":"5400000"},{"uuid":"a82c0066-7f22-32d6-a95e-88a7112d7504","title":"SUNTV 商业计划书_2015黄烈版","activityid":"746060","qrcode":"","cover":"http://ts3.tvm.cn/ky5d4g/e8/bb/e8bbacf2-5395-b249-3ac1-894ff8905e2c/userimg.jpg","mpuser":"blade.big@gmail.com","addtime":"2016-01-18 12:05:20","startTime":"2016-01-18 12:05:20","startTimeStamp":"1453089920000","endTime":"2016-01-18 12:18:26","coursestatus":"2","boxalias":"30-59-B7-04-3F-5A","boxid":"30-59-B7-04-3F-5A","desc":"","type":"2","videoUrl":"","download":"1","courseDuration":"786000"},{"uuid":"b6f6dfe6-d622-3875-b22d-ae8fc0d8be51","title":"手机直播-新版-test001","activityid":"162200","qrcode":"","cover":"http://ts3.tvm.cn/ky5d4g/0c/b7/0cb754bf-9e61-ae69-2810-c02aeba84136/userimg.jpg","mpuser":"blade.big@gmail.com","addtime":"2016-01-18 11:53:06","startTime":"2016-01-18 11:53:06","startTimeStamp":"1453089186000","endTime":"2016-01-18 12:04:06","coursestatus":"2","boxalias":"30-59-B7-04-3F-5A","boxid":"30-59-B7-04-3F-5A","desc":"","type":"2","videoUrl":"http://ts3.tvm.cn/ky5d4g/27/b7/27b731a2-f5a3-405b-2ada-b2c15850e9c2/mp4h.mp4","download":"1","courseDuration":"660000"},{"uuid":"17691e0c-2647-3626-b9e6-6149f3a80a1a","title":"林总Surface pro3集成ICE+教师端+手机直播-测试-01","activityid":"361111","qrcode":"","cover":"http://ts3.tvm.cn/ky5d4g/f3/7b/f37b7f97-698a-c5a4-6366-865af64f8128/userimg.jpg","mpuser":"blade.big@gmail.com","addtime":"2015-12-24 14:24:25","startTime":"2015-12-24 14:24:25","startTimeStamp":"1450938265000","endTime":"2015-12-24 14:34:31","coursestatus":"2","boxalias":"30-59-B7-04-3F-5A","boxid":"30-59-B7-04-3F-5A","desc":"","type":"2","videoUrl":"","download":"1","courseDuration":"606000"},{"uuid":"ea3c2fdf-beb1-3d36-ab6e-370b054c96e5","title":"手机直播实验-2","activityid":"745498","qrcode":"","cover":"http://ts3.tvm.cn/ky5d4g/f0/15/f01569bf-0f83-0cf2-5f09-e4fb06995f30/userimg.jpg","mpuser":"blade.big@gmail.com","addtime":"2015-12-24 13:52:49","startTime":"2015-12-24 13:52:49","startTimeStamp":"1450936369000","endTime":"2015-12-24 14:19:19","coursestatus":"2","boxalias":"30-59-B7-04-3F-5A","boxid":"30-59-B7-04-3F-5A","desc":"","type":"0","videoUrl":"","download":"1","courseDuration":"1590000"},{"uuid":"41384349-020b-396f-a839-2de29d5f87e4","title":"Zaker_天脉新","activityid":"134818","qrcode":"","cover":"http://ts3.tvm.cn/ky5d4g/46/8a/468aa8f6-8283-d4e9-23f3-1830232ceff6/userimg.jpg","mpuser":"blade.big@gmail.com","addtime":"2015-12-22 16:48:01","startTime":"2015-12-22 16:48:01","startTimeStamp":"1450774081000","endTime":"2015-12-22 17:10:37","coursestatus":"2","boxalias":"30-59-B7-04-3F-5A","boxid":"30-59-B7-04-3F-5A","desc":"","type":"0","videoUrl":"","download":"1","courseDuration":"1356000"},{"uuid":"49a26253-e7b3-37ba-85e2-afdbd9deca55","title":"演示文稿1","activityid":"919448","qrcode":"","cover":"http://ts3.tvm.cn/ky5d4g/a6/f7/a6f754b1-c8a9-4ebd-4ed9-8a95bebabdc9/userimg.jpg","mpuser":"blade.big@gmail.com","addtime":"2015-12-18 18:22:42","startTime":"2015-12-18 18:22:42","startTimeStamp":"1450434162000","endTime":"2015-12-18 19:52:42","coursestatus":"2","boxalias":"BC-EE-7B-89-BD-BB","boxid":"BC-EE-7B-89-BD-BB","desc":"","type":"0","videoUrl":"","download":"1","courseDuration":"5400000"},{"uuid":"5bd6f09e-7ca7-3800-8ab6-a70a5fc74262","title":"英语课 ","activityid":"596438","qrcode":"","cover":"http://img1.s3.tvm.cn/s3irs/g2r2/43/55/43552f79-0706-dfe3-6e44-f3c46f48791d/userimg.jpg","mpuser":"blade.big@gmail.com","addtime":"2015-04-10 10:33:24","startTime":"2015-04-10 10:33:24","startTimeStamp":"1428633204000","endTime":"2015-04-10 11:20:27","coursestatus":"2","boxalias":"FC-AA-14-22-3A-DF","boxid":"FC-AA-14-22-3A-DF","desc":"","type":"2","videoUrl":"http://video.s3.tvm.cn/s3/g2r2/78/2c/782ce8ee-ef31-b718-61ad-0c75e052628c/mp4h.mp4","download":"","courseDuration":"2823000"},{"uuid":"edbae2a1-1a19-39fb-a95e-69d1340eeb80","title":"第9讲近代中国经济结构的变动","activityid":"523126","qrcode":"","cover":"http://img1.s3.tvm.cn/s3irs/g2r2/c3/53/c3531b26-c304-8e07-e77d-04c04efa363e/userimg.jpg","mpuser":"blade.big@gmail.com","addtime":"2015-04-10 09:40:05","startTime":"2015-04-10 09:40:05","startTimeStamp":"1428630005000","endTime":"2015-04-10 10:25:56","coursestatus":"2","boxalias":"FC-AA-14-22-3A-DF","boxid":"FC-AA-14-22-3A-DF","desc":"","type":"2","videoUrl":"http://video.s3.tvm.cn/s3/g2r2/f9/5a/f95a7865-ee90-c315-3012-fb47420611c1/mp4h.mp4","download":"","courseDuration":"2751000"},{"uuid":"02bca02f-826b-3749-8284-218205bb6487","title":"2015-4-10 数学课","activityid":"822071","qrcode":"","cover":"http://img1.s3.tvm.cn/s3irs/g2r2/46/82/4682f193-41e7-846b-c57d-02b15f2a70f9/userimg.jpg","mpuser":"blade.big@gmail.com","addtime":"2015-04-10 08:25:42","startTime":"2015-04-10 08:25:42","startTimeStamp":"1428625542000","endTime":"2015-04-10 09:11:36","coursestatus":"2","boxalias":"FC-AA-14-22-3A-DF","boxid":"FC-AA-14-22-3A-DF","desc":"","type":"2","videoUrl":"http://video.s3.tvm.cn/s3/g2r2/ae/ad/aead57d0-5e0b-455d-4162-75f26ac235dd/mp4h.mp4","download":"","courseDuration":"2754000"},{"uuid":"07a3a03c-ecaa-30d6-8492-8f68c93dbe15","title":"物理课","activityid":"957649","qrcode":"","cover":"http://img1.s3.tvm.cn/s3irs/g2r2/00/25/0025cd57-440a-8230-3e24-779aad2372ca/userimg.jpg","mpuser":"blade.big@gmail.com","addtime":"2015-04-10 07:31:05","startTime":"2015-04-10 07:31:05","startTimeStamp":"1428622265000","endTime":"2015-04-10 08:17:19","coursestatus":"2","boxalias":"FC-AA-14-22-3A-DF","boxid":"FC-AA-14-22-3A-DF","desc":"","type":"2","videoUrl":"http://video.s3.tvm.cn/s3/g2r2/50/b6/50b6b9c8-eaf8-13d0-99ac-af87f87abf6d/mp4h.mp4","download":"","courseDuration":"2774000"},{"uuid":"0fa63971-c3ef-339c-a408-0a640277b7e9","title":"第六课第一二框新课件","activityid":"456358","qrcode":"","cover":"http://img1.s3.tvm.cn/s3irs/g2r2/55/26/55262464-3c3d-56dd-4474-87694496b46c/userimg.jpg","mpuser":"blade.big@gmail.com","addtime":"2015-04-09 14:57:33","startTime":"2015-04-09 14:57:33","startTimeStamp":"1428562653000","endTime":"2015-04-09 15:42:35","coursestatus":"2","boxalias":"FC-AA-14-22-3A-DF","boxid":"FC-AA-14-22-3A-DF","desc":"","type":"2","videoUrl":"http://video.s3.tvm.cn/s3/g2r2/69/48/6948a690-3a8d-d549-e035-088c4fefc691/mp4h.mp4","download":"","courseDuration":"2702000"},{"uuid":"9ee7b432-f2de-3704-b24d-13bcb148bc66","title":"英语409","activityid":"981888","qrcode":"","cover":"http://img1.s3.tvm.cn/s3irs/g2r2/b6/b1/b6b15e6d-ed5c-a438-c56b-af8fad48ee7d/userimg.jpg","mpuser":"blade.big@gmail.com","addtime":"2015-04-09 13:58:41","startTime":"2015-04-09 13:58:41","startTimeStamp":"1428559121000","endTime":"2015-04-09 14:47:43","coursestatus":"2","boxalias":"FC-AA-14-22-3A-DF","boxid":"FC-AA-14-22-3A-DF","desc":"","type":"2","videoUrl":"http://video.s3.tvm.cn/s3/g2r2/40/18/401841fd-243a-2795-ef67-5fd695145299/mp4h.mp4","download":"","courseDuration":"2942000"},{"uuid":"3b81e96d-d6cd-3df0-9f21-0a1562433ba6","title":"3.2.1直线的点斜式方程-刘春波","activityid":"582345","qrcode":"","cover":"http://img1.s3.tvm.cn/s3irs/g2r2/6f/00/6f00bfc2-5c26-e3c2-3464-f15883f355da/userimg.jpg","mpuser":"blade.big@gmail.com","addtime":"2015-04-09 10:36:59","startTime":"2015-04-09 10:36:59","startTimeStamp":"1428547019000","endTime":"2015-04-09 11:21:42","coursestatus":"2","boxalias":"FC-AA-14-22-3A-DF","boxid":"FC-AA-14-22-3A-DF","desc":"","type":"2","videoUrl":"http://video.s3.tvm.cn/s3/g2r2/d4/5d/d45d459b-6cf4-04ba-b8b4-6c9e46ba6405/mp4h.mp4","download":"","courseDuration":"2683000"},{"uuid":"c8a8fb52-1dbd-3ddd-b94f-e8ada0714473","title":"语文课-祝福","activityid":"325806","qrcode":"","cover":"http://img1.s3.tvm.cn/s3irs/g2r2/be/d5/bed5176a-ec87-b975-978b-ef07a63c9d87/userimg.jpg","mpuser":"blade.big@gmail.com","addtime":"2015-04-09 09:46:07","startTime":"2015-04-09 09:46:07","startTimeStamp":"1428543967000","endTime":"2015-04-09 10:27:23","coursestatus":"2","boxalias":"FC-AA-14-22-3A-DF","boxid":"FC-AA-14-22-3A-DF","desc":"","type":"2","videoUrl":"http://video.s3.tvm.cn/s3/g2r2/1a/c4/1ac48737-0702-93d5-7816-d0cf914920d4/mp4h.mp4","download":"","courseDuration":"2476000"},{"uuid":"23e5b94b-871c-3803-ad04-f79ef167af2a","title":"2.3城市化（一）","activityid":"693846","qrcode":"","cover":"http://img1.s3.tvm.cn/s3irs/g2r2/54/79/54794705-5301-a582-6781-44868c817c0c/userimg.jpg","mpuser":"blade.big@gmail.com","addtime":"2015-04-09 08:25:42","startTime":"2015-04-09 08:25:42","startTimeStamp":"1428539142000","endTime":"2015-04-09 09:11:09","coursestatus":"2","boxalias":"FC-AA-14-22-3A-DF","boxid":"FC-AA-14-22-3A-DF","desc":"","type":"2","videoUrl":"http://video.s3.tvm.cn/s3/g2r2/01/78/01783474-97fd-d06d-358b-d5b49c2a1711/mp4h.mp4","download":"","courseDuration":"2727000"},{"uuid":"fbe4fd89-a6e4-3442-8318-577926e1eed8","title":"化学键与化学反应","activityid":"473245","qrcode":"","cover":"http://img1.s3.tvm.cn/s3irs/g2r2/50/ad/50ad4d24-8c48-bf2f-12f5-aed5f7459531/userimg.jpg","mpuser":"blade.big@gmail.com","addtime":"2015-04-09 07:29:27","startTime":"2015-04-09 07:29:27","startTimeStamp":"1428535767000","endTime":"2015-04-09 08:18:03","coursestatus":"2","boxalias":"FC-AA-14-22-3A-DF","boxid":"FC-AA-14-22-3A-DF","desc":"","type":"2","videoUrl":"http://video.s3.tvm.cn/s3/g2r2/bf/7c/bf7c6149-5223-c58e-2865-854701ca0c17/mp4h.mp4","download":"","courseDuration":"2916000"},{"uuid":"4051195e-e1b7-31a8-b5a9-ac29a4c1e3aa","title":"多媒体互动教室","activityid":"748448","qrcode":"","cover":"","mpuser":"blade.big@gmail.com","addtime":"2015-02-25 15:21:37","startTime":"2015-02-25 15:21:37","startTimeStamp":"1424848897000","endTime":"2015-02-25 16:51:37","coursestatus":"2","boxalias":"AC-22-0B-79-C9-15","boxid":"AC-22-0B-79-C9-15","desc":"","type":"0","videoUrl":"","download":"","courseDuration":"5400000"},{"uuid":"30852646-a6b8-3f6f-b7d2-ffab233e6e94","title":"l.8.7i8o","activityid":"529534","qrcode":"","cover":"http://media.tvmcloud.com/b4/f5/b4f590cf-7f4a-77e9-8b70-33351a45155d/userimg.jpg","mpuser":"blade.big@gmail.com","addtime":"2014-12-15 13:57:39","startTime":"2014-12-15 13:57:39","startTimeStamp":"1418623059541","endTime":"2014-12-15 13:58:35","coursestatus":"2","boxalias":"00-00-00-00-00-00","boxid":"00-00-00-00-00-00","desc":"","type":"1","videoUrl":"","download":"","courseDuration":"55459"},{"uuid":"412815da-d66d-3dbc-96ff-db6a498c4aca","title":"1209-2","activityid":"471642","qrcode":"","cover":"http://media.tvmcloud.com/73/89/73896d3e-17ec-ed1b-cf2f-7526559dd09c/userimg.jpg","mpuser":"blade.big@gmail.com","addtime":"2014-12-09 16:33:35","startTime":"2014-12-09 16:33:35","startTimeStamp":"1418114015000","endTime":"2014-12-09 16:50:29","coursestatus":"2","boxalias":"BC-EE-7B-89-BD-4C","boxid":"BC-EE-7B-89-BD-4C","desc":"","type":"2","videoUrl":"http://video.tvmcloud.com/2b/7b/2b7b5083-8204-7eaa-1fd4-abc72e5f2ba6/mp4h.mp4","download":"","courseDuration":"1014000"},{"uuid":"9ea0a7ab-ba0e-3ec2-b57d-a8f6e9c6df54","title":"第三届世界华文教育大会   示范课","activityid":"247276","qrcode":"","cover":"http://media.tvmcloud.com/ed/ee/edee6adf-4a0e-5e6c-65da-bc5292984e84/userimg.jpg","mpuser":"blade.big@gmail.com","addtime":"2014-12-07 21:42:43","startTime":"2014-12-07 21:42:43","startTimeStamp":"1417959763000","endTime":"2014-12-07 22:02:54","coursestatus":"2","boxalias":"BC-EE-7B-88-4F-69","boxid":"BC-EE-7B-88-4F-69","desc":"","type":"2","videoUrl":"http://video.tvmcloud.com/68/44/684400dd-167a-b04a-fad2-1747fd220595/mp4h.mp4","download":"","courseDuration":"1211000"},{"uuid":"e53c18a0-ef31-3bf1-a97b-c2bcb0e515e9","title":"中安恒昌培训会1205","activityid":"365179","qrcode":"","cover":"http://media.tvmcloud.com/ff/e8/ffe85087-5c7d-bd91-019a-01eb80166e76/userimg.jpg","mpuser":"blade.big@gmail.com","addtime":"2014-12-05 15:06:38","startTime":"2014-12-05 15:06:38","startTimeStamp":"1417763198000","endTime":"2014-12-05 16:36:38","coursestatus":"2","boxalias":"AC-22-0B-7A-20-7A","boxid":"AC-22-0B-7A-20-7A","desc":"","type":"1","videoUrl":"","download":"","courseDuration":"5400000"},{"uuid":"c043985f-d74a-34c9-a3c6-59653afa30ee","title":"11-16-001-js","activityid":"645261","qrcode":"","cover":"http://media.tvmcloud.com/19/c9/19c95237-e186-3db8-567f-17f4fc682d1e/userimg.jpg","mpuser":"blade.big@gmail.com","addtime":"2014-11-16 09:19:27","startTime":"2014-11-16 09:19:27","startTimeStamp":"1416100767000","endTime":"2014-11-16 10:49:27","coursestatus":"2","boxalias":"AC-22-0B-79-C4-97","boxid":"AC-22-0B-79-C4-97","desc":"","type":"2","videoUrl":"http://video.tvmcloud.com/7e/b3/7eb3bb1e-9197-b7f0-410b-8b91fa4644e3/mp4h.mp4","download":"","courseDuration":"5400000"},{"uuid":"c0fee718-6609-37f1-ad02-42934680e7f6","title":"jiasheng","activityid":"318418","qrcode":"","cover":"http://media.tvmcloud.com/2a/e3/2ae37465-11e7-84dd-dd4b-40aef5ce460a/userimg.jpg","mpuser":"blade.big@gmail.com","addtime":"2014-10-31 11:26:02","startTime":"2014-10-31 11:26:02","startTimeStamp":"1414725962000","endTime":"2014-10-31 12:56:02","coursestatus":"2","boxalias":"AC-22-0B-79-C4-97","boxid":"AC-22-0B-79-C4-97","desc":"","type":"2","videoUrl":"http://video.tvmcloud.com/1a/fd/1afd22a1-cfa0-a51a-8b45-0cb43184939c/mp4h.mp4","download":"","courseDuration":"5400000"},{"uuid":"f7afcb9b-e941-3cfb-8898-d3239db62779","title":"测试与爱录课录播对接2","activityid":"246660","qrcode":"","cover":"http://media.tvmcloud.com/bd/f2/bdf2481d-25ae-b483-129f-6ebac75548ae/userimg.jpg","mpuser":"blade.big@gmail.com","addtime":"2014-10-24 14:09:20","startTime":"2014-10-24 14:09:20","startTimeStamp":"1414130960000","endTime":"2014-10-24 14:35:44","coursestatus":"2","boxalias":"AC-22-0B-79-C4-97","boxid":"AC-22-0B-79-C4-97","desc":"","type":"2","videoUrl":"http://video.tvmcloud.com/35/71/3571f3e8-0012-0ee1-1427-b6429c917621/mp4h.mp4","download":"","courseDuration":"1584000"},{"uuid":"db957c62-6a8c-37a2-b231-adfbf51e20eb","title":"哈哈哈","activityid":"1788","qrcode":"","cover":"http://media.tvmcloud.com/96/b1/96b1c32b-7b39-95df-2aeb-22907284e02a/userimg.jpg","mpuser":"blade.big@gmail.com","addtime":"2014-05-28 14:24:03","startTime":"2014-05-28 14:24:03","startTimeStamp":"1401258243000","endTime":"2014-05-28 15:54:03","coursestatus":"2","boxalias":"AC-22-0B-79-C9-15","boxid":"AC-22-0B-79-C9-15","desc":"","type":"1","videoUrl":"","download":"","courseDuration":"5400000"}]}